{
  "_comment": "Copy this file to config.json and fill in your values. config.json is gitignored.",

  "base_url": "https://YOUR_CRIBL_HOST:9000",
  "cribl_urls": [
    "https://cribl-azn.example.com:9000",
    "https://cribl-azs.example.com:9000"
  ],
  "elk_urls": [
    "https://elk-azn.example.com:9200",
    "https://elk-azs.example.com:9200"
  ],
  "skip_ssl": true,

  "credentials": {
    "_comment": "Use token OR username+password. Token takes priority if both are set. Leave fields blank to be prompted at runtime.",
    "token": "",
    "username": "",
    "password": ""
  },

  "route_templates": {
    "azn": "route_template_azn.json",
    "azs": "route_template_azs.json"
  },
  "dest_prefixes": {
    "azn": "abcd-blob-storage-northcentralus",
    "azs": "abcd-blob-storage-southcentralus"
  },
  "snapshot_dir": "cribl_snapshots",
  "min_existing_total_routes": 1,
  "diff_lines": 3,

  "workspaces": {
    "dev": {
      "worker_group": "dev",
      "dest_templates": {
        "azn": "blob_dest_template_azn_dev.json",
        "azs": "blob_dest_template_azs_dev.json"
      },
      "description": "Development workspace"
    },
    "test": {
      "worker_group": "test",
      "dest_templates": {
        "azn": "blob_dest_template_azn_test.json",
        "azs": "blob_dest_template_azs_test.json"
      },
      "description": "Test workspace"
    },
    "prod": {
      "worker_group": "prod",
      "dest_templates": {
        "azn": "blob_dest_template_azn_prod.json",
        "azs": "blob_dest_template_azs_prod.json"
      },
      "description": "Production workspace",
      "require_allow": true
    }
  },

  "_workspace_options_reference": {
    "_comment": "Optional fields you can add to any workspace entry:",
    "base_url": "overrides the global base_url for this workspace — use this to point to a different Cribl cluster",
    "routes_table": "route table name used in GET/PATCH /routes/{routes_table} — defaults to the worker_group name",
    "skip_ssl": "true/false — overrides global skip_ssl for this workspace only",
    "require_allow": "true — forces the user to type ALLOW before any writes",
    "route_template": "path to a per-workspace route template override (skips region lookup)",
    "dest_template": "path to a per-workspace dest template override (skips region lookup)",
    "description": "human-readable label shown in the TARGET banner"
  }
}
